hlre/__init__.py
hlre/__main__.py
hlre/hlre.py
hlre/test_hlre.py
hlre-0.1.0.dist-info/METADATA
hlre-0.1.0.dist-info/WHEEL
hlre-0.1.0.dist-info/entry_points.txt
hlre-0.1.0.dist-info/top_level.txt
hlre-0.1.0.dist-info/RECORD
