Metadata-Version: 2.1
Name: hlre
Version: 0.1.0
Summary: Interactively highlight regular expression matches
Home-page: https://github.com/zgulde/hlre
Author: Zach Gulde
Author-email: zachgulde@gmail.com
License: UNKNOWN
Platform: UNKNOWN
Classifier: Programming Language :: Python :: 3
Classifier: License :: OSI Approved :: MIT License
Classifier: Operating System :: OS Independent
Requires-Dist: prompt-toolkit (>=2)
